CDEF-1.0.dist-info/RECORD
CDEF-1.0.dist-info/LICENSE
CDEF-1.0.dist-info/WHEEL
CDEF-1.0.dist-info/top_level.txt
CDEF-1.0.dist-info/METADATA
CDEF/CDEF_main.py
CDEF/cloud.py
CDEF/__init__.py
CDEF/debyer.cpython-37m-darwin.so
CDEF/sobol_seq.py
CDEF/.dylibs/libomp.dylib
