Metadata-Version: 2.1
Name: CDEF
Version: 1.0
Summary: Compute small-angle scattering form factors for arbitrary shapes
Home-page: UNKNOWN
Author: Jerome Deumer
Author-email: jerome.deumer@ptb.de
License: UNKNOWN
Platform: UNKNOWN
Classifier: Development Status :: 4 - Beta
Classifier: Intended Audience :: Science/Research
Classifier: Topic :: Scientific/Engineering :: Physics
Classifier: License :: OSI Approved :: GNU General Public License v3 or later (GPLv3+)
Classifier: Programming Language :: Python :: 3
Requires-Python: >=3.6
License-File: LICENSE
